odoo/addons/shopfloor_mobile_base/README.rst
odoo/addons/shopfloor_mobile_base/__init__.py
odoo/addons/shopfloor_mobile_base/__manifest__.py
odoo/addons/shopfloor_mobile_base/utils.py
odoo/addons/shopfloor_mobile_base/controllers/__init__.py
odoo/addons/shopfloor_mobile_base/controllers/main.py
odoo/addons/shopfloor_mobile_base/i18n/es_AR.po
odoo/addons/shopfloor_mobile_base/i18n/it.po
odoo/addons/shopfloor_mobile_base/i18n/shopfloor_mobile_base.pot
odoo/addons/shopfloor_mobile_base/readme/CONTRIBUTORS.md
odoo/addons/shopfloor_mobile_base/readme/CREDITS.md
odoo/addons/shopfloor_mobile_base/readme/DESCRIPTION.md
odoo/addons/shopfloor_mobile_base/readme/HISTORY.md
odoo/addons/shopfloor_mobile_base/readme/ROADMAP.md
odoo/addons/shopfloor_mobile_base/readme/USAGE.md
odoo/addons/shopfloor_mobile_base/static/description/icon.png
odoo/addons/shopfloor_mobile_base/static/description/index.html
odoo/addons/shopfloor_mobile_base/static/src/fetch.js
odoo/addons/shopfloor_mobile_base/static/src/homepage.esm.js
odoo/addons/shopfloor_mobile_base/static/src/loginpage.esm.js
odoo/addons/shopfloor_mobile_base/static/src/main.esm.js
odoo/addons/shopfloor_mobile_base/static/src/mixin.esm.js
odoo/addons/shopfloor_mobile_base/static/src/router.esm.js
odoo/addons/shopfloor_mobile_base/static/src/theme.esm.js
odoo/addons/shopfloor_mobile_base/static/src/utils.esm.js
odoo/addons/shopfloor_mobile_base/static/src/assets/logo.png
odoo/addons/shopfloor_mobile_base/static/src/assets/icons/android-icon-144x144.png
odoo/addons/shopfloor_mobile_base/static/src/assets/icons/android-icon-192x192.png
odoo/addons/shopfloor_mobile_base/static/src/assets/icons/android-icon-36x36.png
odoo/addons/shopfloor_mobile_base/static/src/assets/icons/android-icon-48x48.png
odoo/addons/shopfloor_mobile_base/static/src/assets/icons/android-icon-72x72.png
odoo/addons/shopfloor_mobile_base/static/src/assets/icons/android-icon-96x96.png
odoo/addons/shopfloor_mobile_base/static/src/assets/icons/apple-icon-114x114.png
odoo_addon_shopfloor_mobile_base-18.0.1.2.0.dist-info/METADATA
odoo_addon_shopfloor_mobile_base-18.0.1.2.0.dist-info/WHEEL
odoo_addon_shopfloor_mobile_base-18.0.1.2.0.dist-info/top_level.txt
odoo_addon_shopfloor_mobile_base-18.0.1.2.0.dist-info/RECORD
