Metadata-Version: 2.1
Name: odoo-addon-shopfloor_mobile_base
Version: 18.0.1.2.0
Requires-Python: >=3.10
Requires-Dist: odoo-addon-shopfloor_base==18.0.*
Requires-Dist: odoo==18.0.*
Summary: Mobile frontend for WMS Shopfloor app
Home-page: https://github.com/OCA/shopfloor-app
License: LGPL-3
Author: Camptocamp, BCIM, Akretion, Odoo Community Association (OCA)
Author-email: support@odoo-community.org
Classifier: Programming Language :: Python
Classifier: Framework :: Odoo
Classifier: Framework :: Odoo :: 18.0
Classifier: License :: OSI Approved :: GNU Lesser General Public License v3 (LGPLv3)
Classifier: Development Status :: 4 - Beta
